django_glue/__init__.py
django_glue/conf.py
django_glue/constants.py
django_glue/context_processors.py
django_glue/decorators.py
django_glue/middleware.py
django_glue/settings.py
django_glue/shortcuts.py
django_glue/urls.py
django_glue/utils.py
django_glue/views_ajax.py
django_glue/access/__init__.py
django_glue/access/access.py
django_glue/access/actions.py
django_glue/access/decorators.py
django_glue/form/__init__.py
django_glue/form/field/__init__.py
django_glue/form/field/enums.py
django_glue/form/field/factories.py
django_glue/form/field/field.py
django_glue/form/field/attributes/__init__.py
django_glue/form/field/attributes/attributes.py
django_glue/form/field/attributes/builder.py
django_glue/form/field/attributes/factories.py
django_glue/form/field/attributes/maps.py
django_glue/glue/__init__.py
django_glue/glue/enums.py
django_glue/glue/glue.py
django_glue/glue/post_data.py
django_glue/glue/function/__init__.py
django_glue/glue/function/actions.py
django_glue/glue/function/glue.py
django_glue/glue/function/handlers.py
django_glue/glue/function/maps.py
django_glue/glue/function/post_data.py
django_glue/glue/function/response_data.py
django_glue/glue/function/session_data.py
django_glue/glue/model_object/__init__.py
django_glue/glue/model_object/actions.py
django_glue/glue/model_object/glue.py
django_glue/glue/model_object/handlers.py
django_glue/glue/model_object/maps.py
django_glue/glue/model_object/response_data.py
django_glue/glue/model_object/session_data.py
django_glue/glue/model_object/tools.py
django_glue/glue/model_object/fields/__init__.py
django_glue/glue/model_object/fields/glue.py
django_glue/glue/model_object/fields/seralizers.py
django_glue/glue/model_object/fields/tools.py
django_glue/glue/model_object/fields/utils.py
django_glue/glue/query_set/__init__.py
django_glue/glue/query_set/actions.py
django_glue/glue/query_set/glue.py
django_glue/glue/query_set/handlers.py
django_glue/glue/query_set/maps.py
django_glue/glue/query_set/post_data.py
django_glue-0.8.12.dist-info/licenses/LICENSE.md
django_glue-0.8.12.dist-info/METADATA
django_glue-0.8.12.dist-info/WHEEL
django_glue-0.8.12.dist-info/top_level.txt
django_glue-0.8.12.dist-info/RECORD
