Metadata-Version: 2.4
Name: django-glue
Version: 0.8.12
Summary: Industrial Strength Glue for Django Backends and Frontends!
Author-email: Austin Sauer <austins@stratusadv.com>, Nathan Johnson <nathanj@stratusadv.com>
License: Copyright (c) 2024 Stratus Advanced Technologies and Contributors.
Project-URL: Homepage, https://django-glue.stratusadv.com
Project-URL: Documentation, https://django-glue.stratusadv.com
Project-URL: Repository, https://github.com/stratusadv/django-glue
Project-URL: Changelog, https://django-glue.stratusadv.com/changelog/changelog/
Keywords: django,glue,backend,frontend,javascript,active server pages
Classifier: Development Status :: 5 - Production/Stable
Classifier: Environment :: Web Environment
Classifier: Framework :: Django
Classifier: Framework :: Django :: 3
Classifier: Framework :: Django :: 4
Classifier: Framework :: Django :: 5
Classifier: License :: OSI Approved :: MIT License
Classifier: Operating System :: OS Independent
Classifier: Programming Language :: JavaScript
Classifier: Programming Language :: Python :: 3.11
Classifier: Programming Language :: Python :: 3.12
Classifier: Programming Language :: Python :: 3.13
Classifier: Topic :: Internet :: WWW/HTTP
Classifier: Topic :: Internet :: WWW/HTTP :: Dynamic Content
Classifier: Topic :: Software Development :: Libraries :: Python Modules
Requires-Python: >=3.11
License-File: LICENSE.md
Requires-Dist: django>=5
Provides-Extra: development
Requires-Dist: pyright; extra == "development"
Requires-Dist: twine; extra == "development"
Requires-Dist: build; extra == "development"
Requires-Dist: setuptools; extra == "development"
Requires-Dist: wheel; extra == "development"
Requires-Dist: playwright; extra == "development"
Requires-Dist: django-spire==0.14.0; extra == "development"
Provides-Extra: documentation
Requires-Dist: mkdocs; extra == "documentation"
Requires-Dist: markdown-exec[ansi]; extra == "documentation"
Requires-Dist: mkdocs-include-markdown-plugin; extra == "documentation"
Requires-Dist: mkdocs-material; extra == "documentation"
Requires-Dist: mkdocs-table-reader-plugin; extra == "documentation"
Requires-Dist: mkdocstrings-python; extra == "documentation"
Requires-Dist: openpyxl; extra == "documentation"
Dynamic: license-file
